{"Popular times": {}, "About": {"Accessibility": ["Wheelchair-accessible car park", "Wheelchair-accessible entrance"]}, "url": "https://www.google.com/maps/place/Bukit+Panjang+Zone+%279%27+Residents+Committee/data=!4m7!3m6!1s0x31da11a646526e1f:0xa5ce029cd978f26b!8m2!3d1.3853698!4d103.7704965!16s%2Fg%2F1td7f7b6!19sChIJH25SRqYR2jERa_J42ZwCzqU?authuser=0&hl=en&rclk=1", "status": "success", "place_id": "ChIJH25SRqYR2jERa_J42ZwCzqU", "timestamp": "2024-12-09 16:39:57.907099", "metadata": {"Copy address": "\ue0c8\n434 Bukit Panjang Ring Rd, Block 434 Block 434, Singapore 670434", "Copy phone number": "\ue0b0\n6760 1231", "Call phone number": "\ue0b0", "Copy plus code": "\uf186\n9QPC+45 Singapore"}}