{"Popular times": {}, "About": {"Accessibility": ["Wheelchair-accessible entrance", "Wheelchair-accessible seating"], "Service options": ["Takeaway", "Dine-in", "Delivery"], "Offerings": ["Coffee"], "Dining options": ["Lunch", "Dinner"], "Amenities": ["Toilets"], "Atmosphere": ["Casual"], "Crowd": ["Groups"], "Planning": ["Accepts reservations"], "Children": ["Good for kids"], "Parking": ["Free parking lot", "Plenty of parking"]}, "url": "https://www.google.com/maps/place/Thai+Me+Up/data=!4m7!3m6!1s0x31da1311c878a80b:0xed64c7ec5a2475d7!8m2!3d1.440893!4d103.7813295!16s%2Fg%2F11kphwn3qn!19sChIJC6h4yBET2jER13UkWuzHZO0?authuser=0&hl=en&rclk=1", "status": "success", "place_id": "ChIJC6h4yBET2jER13UkWuzHZO0", "timestamp": "2024-12-08 13:32:29.351533", "metadata": {"Copy address": "\ue0c8\n10 Marsiling Industrial Estate Rd 1, #01-01, Singapore 739276", "Copy plus code": "\uf186\nCQRJ+9G Singapore"}}