{"Popular times": {}, "About": {"Accessibility": ["Wheelchair-accessible entrance"], "Service options": ["Takeaway", "Dine-in"], "Offerings": ["Small plates"], "Dining options": ["Brunch", "Lunch", "Dinner"], "Atmosphere": ["Casual"], "Crowd": ["Groups"], "Children": ["Good for kids"]}, "url": "https://www.google.com/maps/place/Sembawang+Mrt/data=!4m7!3m6!1s0x31da13d267611c5b:0x7d21da1f7cc19ce9!8m2!3d1.4491118!4d103.8198392!16s%2Fg%2F11svc40h5g!19sChIJWxxhZ9IT2jER6ZzBfB_aIX0?authuser=0&hl=en&rclk=1", "status": "success", "place_id": "ChIJWxxhZ9IT2jER6ZzBfB_aIX0", "timestamp": "2024-12-12 18:46:55.314049", "metadata": {"Copy address": "\ue0c8\n11 Canberra Rd, #01-04, Singapore 759775", "Copy plus code": "\uf186\nCRX9+JW Singapore"}}