{"Popular times": {}, "About": {"Accessibility": ["Wheelchair-accessible seating"], "Service options": ["Delivery", "Takeaway", "Dine-in"], "Offerings": ["Coffee"], "Dining options": ["Breakfast", "Brunch", "Lunch", "Dinner"], "Amenities": ["Toilets"], "Atmosphere": ["Casual"], "Crowd": ["Groups"], "Children": ["Good for kids"], "Parking": ["Paid multi-storey car park", "Paid parking lot"]}, "url": "https://www.google.com/maps/place/51+Noodle+House+%7C+Yishun/data=!4m7!3m6!1s0x31da155bad249b0f:0xf92f74a5128dc960!8m2!3d1.4249457!4d103.8447228!16s%2Fg%2F11flbfr1_v!19sChIJD5skrVsV2jERYMmNEqV0L_k?authuser=0&hl=en&rclk=1", "status": "success", "place_id": "ChIJD5skrVsV2jERYMmNEqV0L_k", "timestamp": "2024-12-11 01:13:26.149708", "metadata": {"Copy address": "\ue0c8\n51 Yishun Ave 11, #01-27, Singapore 768867", "Place an order": "\ue558\nPlace an order", "Copy website": "\ue14d", "Open website": "\ue80b\nm.facebook.com", "Copy plus code": "\uf186\nCRFV+XV Singapore"}}