{"Popular times": {}, "About": {"Accessibility": ["Wheelchair-accessible car park", "Wheelchair-accessible entrance"], "Amenities": ["Toilets"]}, "url": "https://www.google.com/maps/place/MoveMed+Physiotherapy/data=!4m7!3m6!1s0x31da19da46646ab7:0xc786bf948a2bd115!8m2!3d1.3211072!4d103.8443378!16s%2Fg%2F11l5tdjrgc!19sChIJt2pkRtoZ2jERFdEripS_hsc?authuser=0&hl=en&rclk=1", "status": "success", "place_id": "ChIJt2pkRtoZ2jERFdEripS_hsc", "timestamp": "2024-12-09 21:42:12.015915", "metadata": {"Copy address": "\ue0c8\n10 Sinaran Dr, #09-04 Novena Medical Center, Singapore 307506", "Copy website": "\ue14d", "Open website": "\ue80b\nmovemedsg.com", "Copy phone number": "\ue0b0\n9627 2000", "Call phone number": "\ue0b0", "Copy plus code": "\uf186\n8RCV+7P Singapore"}}