{"Popular times": {"Monday": {"6 am.": 0, "7 am.": 0, "8 am.": 25, "9 am.": 42, "10 am.": 75, "11 am.": 46, "12 pm.": 42, "1 pm.": 14, "2 pm.": 17, "3 pm.": 28, "4 pm.": 75, "5 pm.": 75, "6 pm.": 100, "7 pm.": 64, "8 pm.": 71, "9 pm.": 32, "10 pm.": 0, "11 pm.": 0}, "Tuesday": {"6 am.": 0, "7 am.": 0, "8 am.": 0, "9 am.": 3, "10 am.": 7, "11 am.": 3, "12 pm.": 7, "1 pm.": 14, "2 pm.": 28, "3 pm.": 28, "4 pm.": 42, "5 pm.": 53, "6 pm.": 25, "7 pm.": 10, "8 pm.": 0, "9 pm.": 0, "10 pm.": 0, "11 pm.": 0}, "Wednesday": {"6 am.": 0, "7 am.": 0, "8 am.": 17, "9 am.": 28, "10 am.": 14, "11 am.": 7, "12 pm.": 10, "1 pm.": 21, "2 pm.": 53, "3 pm.": 46, "4 pm.": 53, "5 pm.": 17, "6 pm.": 7, "7 pm.": 0, "8 pm.": 0, "9 pm.": 0, "10 pm.": 0, "11 pm.": 0}, "Thursday": {"6 am.": 0, "7 am.": 0, "8 am.": 7, "9 am.": 10, "10 am.": 17, "11 am.": 39, "12 pm.": 28, "1 pm.": 21, "2 pm.": 35, "3 pm.": 75, "4 pm.": 67, "5 pm.": 32, "6 pm.": 14, "7 pm.": 7, "8 pm.": 7, "9 pm.": 7, "10 pm.": 0, "11 pm.": 0}, "Friday": {"6 am.": 0, "7 am.": 0, "8 am.": 7, "9 am.": 17, "10 am.": 17, "11 am.": 32, "12 pm.": 25, "1 pm.": 28, "2 pm.": 46, "3 pm.": 42, "4 pm.": 17, "5 pm.": 17, "6 pm.": 42, "7 pm.": 89, "8 pm.": 85, "9 pm.": 53, "10 pm.": 0, "11 pm.": 0}, "Saturday": {"6 am.": 0, "7 am.": 0, "8 am.": 53, "9 am.": 42, "10 am.": 14, "11 am.": 21, "12 pm.": 42, "1 pm.": 57, "2 pm.": 35, "3 pm.": 17, "4 pm.": 17, "5 pm.": 10, "6 pm.": 25, "7 pm.": 46, "8 pm.": 75, "9 pm.": 39, "10 pm.": 0, "11 pm.": 0}, "Sunday": {"6 am.": 0, "7 am.": 0, "8 am.": 28, "9 am.": 60, "10 am.": 78, "11 am.": 64, "12 pm.": 32, "1 pm.": 25, "2 pm.": 28, "3 pm.": 17, "4 pm.": 17, "5 pm.": 17, "6 pm.": 14, "7 pm.": 21, "8 pm.": 10, "9 pm.": 17, "10 pm.": 0, "11 pm.": 0}}, "About": {"Accessibility": ["Wheelchair-accessible car park", "Wheelchair-accessible entrance"], "Service options": ["Delivery", "Takeaway", "Dine-in"], "Offerings": ["Coffee", "Small plates"], "Dining options": ["Brunch", "Lunch", "Dinner"], "Atmosphere": ["Casual"], "Crowd": ["Groups"], "Payments": ["Credit cards"], "Children": ["Good for kids"]}, "url": "https://www.google.com/maps/place/Deliz+Cafe/data=!4m7!3m6!1s0x31da3d26af76352d:0x9046149d2def6bc9!8m2!3d1.3426215!4d103.9529998!16s%2Fg%2F11fqbv9m5g!19sChIJLTV2ryY92jERyWvvLZ0URpA?authuser=0&hl=en&rclk=1", "status": "success", "place_id": "ChIJLTV2ryY92jERyWvvLZ0URpA", "timestamp": "2024-12-09 17:02:51.795751", "metadata": {"Copy address": "\ue0c8\n3 Simei Street 6, #B1-K6, Eastpoint Mall, 3 Simei Street 6, #B1-K6, Singapore 528833", "Place an order": "\ue558\nPlace an order", "Copy phone number": "\ue0b0\n6612 1122", "Call phone number": "\ue0b0", "Copy plus code": "\uf186\n8XV3+25 Singapore"}}