{"Popular times": {}, "About": {"Accessibility": ["Wheelchair-accessible car park"], "Service options": ["Delivery", "In-store shopping", "On-site services"], "Payments": ["Credit cards", "Debit cards", "NFC mobile payments", "Credit cards"]}, "url": "https://www.google.com/maps/place/Nova+Furnishing+@+Tradehub+21/data=!4m7!3m6!1s0x31da107567e322fb:0xb813c0bccaa575ef!8m2!3d1.3276155!4d103.7530613!16s%2Fg%2F1tgj6bjw!19sChIJ-yLjZ3UQ2jER73WlyrzAE7g?authuser=0&hl=en&rclk=1", "status": "success", "place_id": "ChIJ-yLjZ3UQ2jER73WlyrzAE7g", "timestamp": "2024-12-11 12:52:19.663749", "metadata": {"Copy address": "\ue0c8\nNo.8 Boon Lay Way, #01-06 to #01-12 8@TradeHub 21, 609964", "Copy website": "\ue14d", "Open website": "\ue80b\nnovafurnishing.com", "Copy phone number": "\ue0b0\n6896 7882", "Call phone number": "\ue0b0", "Copy plus code": "\uf186\n8QH3+26 Singapore"}}