{"Popular times": {}, "About": {"Accessibility": ["Wheelchair-accessible car park", "Wheelchair-accessible seating"], "Service options": ["Takeaway", "Dine-in"], "Offerings": ["Small plates"], "Dining options": ["Lunch"], "Amenities": ["Toilets"], "Atmosphere": ["Casual"], "Crowd": ["Groups"], "Planning": ["Accepts reservations"], "Children": ["Good for kids"]}, "url": "https://www.google.com/maps/place/Ah+Wah+Rojak/data=!4m7!3m6!1s0x31da22b666c6399f:0x2635a25c96e511a8!8m2!3d1.320547!4d103.9355572!16s%2Fg%2F11cjpcydsr!19sChIJnznGZrYi2jERqBHlllyiNSY?authuser=0&hl=en&rclk=1", "status": "success", "place_id": "ChIJnznGZrYi2jERqBHlllyiNSY", "timestamp": "2024-12-08 11:40:38.416240", "metadata": {"Copy address": "\ue0c8\n16 Bedok S Rd, #01-36, Singapore 460016", "Copy plus code": "\uf186\n8WCP+66 Singapore"}}