{"Popular times": {"Monday": {"4 am.": 8, "5 am.": 8, "6 am.": 15, "7 am.": 23, "8 am.": 30, "9 am.": 36, "10 am.": 40, "11 am.": 38, "1 pm.": 30, "2 pm.": 27, "3 pm.": 26, "4 pm.": 27, "5 pm.": 32, "6 pm.": 39, "7 pm.": 52, "8 pm.": 57, "9 pm.": 61, "10 pm.": 57, "11 pm.": 59, "12 am.": 43, "1 am.": 30, "2 am.": 18, "3 am.": 10}, "Tuesday": {"4 am.": 9, "5 am.": 10, "6 am.": 19, "7 am.": 30, "8 am.": 33, "9 am.": 31, "10 am.": 30, "11 am.": 30, "12 pm.": 37, "1 pm.": 32, "2 pm.": 30, "3 pm.": 25, "4 pm.": 24, "5 pm.": 28, "6 pm.": 34, "7 pm.": 40, "8 pm.": 45, "9 pm.": 54, "10 pm.": 63, "11 pm.": 70, "12 am.": 55, "1 am.": 37, "2 am.": 25, "3 am.": 12}, "Wednesday": {"4 am.": 10, "5 am.": 9, "6 am.": 18, "7 am.": 31, "8 am.": 33, "9 am.": 32, "10 am.": 27, "11 am.": 30, "12 pm.": 30, "1 pm.": 28, "2 pm.": 23, "3 pm.": 22, "4 pm.": 25, "5 pm.": 28, "6 pm.": 36, "7 pm.": 41, "8 pm.": 48, "9 pm.": 60, "10 pm.": 65, "11 pm.": 68, "12 am.": 52, "1 am.": 40, "2 am.": 31, "3 am.": 18}, "Thursday": {"4 am.": 9, "5 am.": 10, "6 am.": 20, "7 am.": 31, "8 am.": 34, "9 am.": 32, "10 am.": 27, "11 am.": 26, "12 pm.": 29, "1 pm.": 25, "2 pm.": 23, "3 pm.": 21, "4 pm.": 27, "5 pm.": 34, "6 pm.": 48, "7 pm.": 53, "8 pm.": 57, "9 pm.": 60, "10 pm.": 64, "11 pm.": 67, "12 am.": 56, "1 am.": 41, "2 am.": 26, "3 am.": 15}, "Friday": {"4 am.": 13, "5 am.": 12, "6 am.": 21, "7 am.": 30, "8 am.": 33, "9 am.": 32, "10 am.": 31, "11 am.": 32, "12 pm.": 33, "1 pm.": 28, "2 pm.": 24, "3 pm.": 22, "4 pm.": 26, "5 pm.": 34, "6 pm.": 41, "7 pm.": 45, "8 pm.": 50, "9 pm.": 62, "10 pm.": 68, "11 pm.": 72, "12 am.": 58, "1 am.": 43, "2 am.": 28, "3 am.": 18}, "Saturday": {"4 am.": 13, "5 am.": 15, "6 am.": 26, "7 am.": 38, "8 am.": 40, "9 am.": 32, "10 am.": 27, "11 am.": 27, "12 pm.": 32, "1 pm.": 32, "2 pm.": 30, "3 pm.": 22, "4 pm.": 20, "5 pm.": 24, "6 pm.": 30, "7 pm.": 39, "8 pm.": 54, "9 pm.": 69, "10 pm.": 79, "11 pm.": 79, "12 am.": 60, "1 am.": 42, "2 am.": 28, "3 am.": 17}, "Sunday": {"4 am.": 10, "5 am.": 15, "6 am.": 24, "7 am.": 37, "8 am.": 47, "9 am.": 44, "10 am.": 39, "11 am.": 32, "12 pm.": 31, "1 pm.": 30, "2 pm.": 25, "3 pm.": 20, "4 pm.": 19, "5 pm.": 20, "6 pm.": 30, "7 pm.": 42, "8 pm.": 56, "9 pm.": 74, "10 pm.": 90, "11 pm.": 100, "12 am.": 81, "1 am.": 58, "2 am.": 33, "3 am.": 17}}, "About": {"Accessibility": ["Wheelchair-accessible car park", "Wheelchair-accessible entrance"], "Service options": ["Outdoor seating", "No-contact delivery", "Delivery", "On-site services", "Takeaway", "Dine-in"], "Offerings": ["Coffee", "Late-night food", "Small plates"], "Dining options": ["Breakfast", "Brunch", "Lunch", "Dinner", "Seating"], "Amenities": ["Toilets"], "Atmosphere": ["Casual"], "Crowd": ["Groups"], "Planning": ["Accepts reservations"], "Children": ["Good for kids"], "Parking": ["Paid parking lot", "Plenty of parking"]}, "url": "https://www.google.com/maps/place/KNS+Restaurant/data=!4m7!3m6!1s0x31da0feb1c04bb81:0xf65359dc4f9abc23!8m2!3d1.3352247!4d103.6957382!16s%2Fg%2F11f77b_tyq!19sChIJgbsEHOsP2jERI7yaT9xZU_Y?authuser=0&hl=en&rclk=1", "status": "success", "place_id": "ChIJgbsEHOsP2jERI7yaT9xZU_Y", "timestamp": "2024-12-08 12:05:34.008130", "metadata": {"Copy address": "\ue0c8\n990 Jurong West Street 93, #01-01, Singapore 640990", "Place an order": "\ue558\nPlace an order\nfoodpanda.sg", "Copy website": "\ue14d", "Open website": "\ue80b\nknsrestaurant.com", "Copy phone number": "\ue0b0\n6816 1633", "Call phone number": "\ue0b0", "Copy plus code": "\uf186\n8MPW+37 Singapore"}}