{"Popular times": {"Monday": {"6 am.": 0, "7 am.": 0, "8 am.": 0, "9 am.": 0, "10 am.": 75, "11 am.": 84, "12 pm.": 88, "1 pm.": 85, "2 pm.": 74, "3 pm.": 64, "4 pm.": 63, "5 pm.": 70, "6 pm.": 76, "7 pm.": 69, "8 pm.": 49, "9 pm.": 28, "10 pm.": 0, "11 pm.": 0}, "Tuesday": {"6 am.": 0, "7 am.": 0, "8 am.": 0, "9 am.": 0, "10 am.": 64, "11 am.": 79, "12 pm.": 89, "1 pm.": 85, "2 pm.": 73, "3 pm.": 61, "4 pm.": 55, "5 pm.": 57, "6 pm.": 62, "7 pm.": 57, "8 pm.": 42, "9 pm.": 25, "10 pm.": 0, "11 pm.": 0}, "Wednesday": {"6 am.": 0, "7 am.": 0, "8 am.": 0, "9 am.": 0, "10 am.": 64, "11 am.": 79, "12 pm.": 89, "1 pm.": 85, "2 pm.": 73, "3 pm.": 61, "4 pm.": 58, "5 pm.": 66, "6 pm.": 75, "7 pm.": 70, "8 pm.": 51, "9 pm.": 31, "10 pm.": 0, "11 pm.": 0}, "Thursday": {"6 am.": 0, "7 am.": 0, "8 am.": 0, "9 am.": 0, "10 am.": 69, "11 am.": 85, "12 pm.": 96, "1 pm.": 92, "2 pm.": 77, "3 pm.": 64, "4 pm.": 60, "5 pm.": 66, "6 pm.": 73, "7 pm.": 68, "8 pm.": 50, "9 pm.": 30, "10 pm.": 0, "11 pm.": 0}, "Friday": {"6 am.": 0, "7 am.": 0, "8 am.": 0, "9 am.": 0, "10 am.": 68, "11 am.": 83, "12 pm.": 92, "1 pm.": 89, "2 pm.": 76, "3 pm.": 65, "4 pm.": 62, "5 pm.": 69, "6 pm.": 77, "7 pm.": 70, "8 pm.": 52, "9 pm.": 30, "10 pm.": 0, "11 pm.": 0}, "Saturday": {"6 am.": 0, "7 am.": 0, "8 am.": 0, "9 am.": 0, "10 am.": 72, "11 am.": 87, "12 pm.": 98, "1 pm.": 94, "2 pm.": 79, "3 pm.": 65, "4 pm.": 61, "5 pm.": 69, "6 pm.": 77, "7 pm.": 72, "8 pm.": 54, "9 pm.": 32, "10 pm.": 0, "11 pm.": 0}, "Sunday": {"6 am.": 0, "7 am.": 0, "8 am.": 0, "9 am.": 0, "10 am.": 88, "11 am.": 97, "12 pm.": 100, "1 pm.": 93, "2 pm.": 79, "3 pm.": 68, "4 pm.": 67, "5 pm.": 76, "6 pm.": 82, "7 pm.": 76, "8 pm.": 55, "9 pm.": 33, "10 pm.": 0, "11 pm.": 0}}, "About": {"Accessibility": ["Wheelchair-accessible car park", "Wheelchair-accessible entrance"], "Service options": ["On-site services"]}, "url": "https://www.google.com/maps/place/Ang+Mo+Kio+Town+Centre/data=!4m7!3m6!1s0x31da16e7905e522d:0xcc7767edfdd1f830!8m2!3d1.3718126!4d103.8469791!16s%2Fg%2F11rg30qs15!19sChIJLVJekOcW2jERMPjR_e1nd8w?authuser=0&hl=en&rclk=1", "status": "success", "place_id": "ChIJLVJekOcW2jERMPjR_e1nd8w", "timestamp": "2024-12-09 23:59:06.986262", "metadata": {"Copy address": "\ue0c8\n720 Ang Mo Kio Ave 6, Singapore 560720", "Copy plus code": "\uf186\n9RCW+PQ Singapore"}}