{"Popular times": {"Monday": {"4 am.": 23, "5 am.": 30, "6 am.": 15, "7 am.": 7, "8 am.": 7, "9 am.": 15, "10 am.": 38, "11 am.": 38, "12 pm.": 38, "1 pm.": 30, "2 pm.": 46, "3 pm.": 23, "4 pm.": 15, "5 pm.": 15, "6 pm.": 38, "7 pm.": 38, "8 pm.": 15, "9 pm.": 0, "10 pm.": 0, "11 pm.": 0, "12 am.": 7, "1 am.": 23, "2 am.": 53, "3 am.": 30}, "Tuesday": {"4 am.": 0, "5 am.": 0, "6 am.": 0, "7 am.": 23, "8 am.": 53, "9 am.": 84, "10 am.": 38, "11 am.": 23, "12 pm.": 23, "1 pm.": 30, "2 pm.": 7, "3 pm.": 0, "4 pm.": 7, "5 pm.": 23, "6 pm.": 15, "7 pm.": 15, "8 pm.": 30, "9 pm.": 23, "10 pm.": 30, "11 pm.": 23, "12 am.": 38, "1 am.": 76, "2 am.": 46, "3 am.": 15}, "Wednesday": {"4 am.": 30, "5 am.": 23, "6 am.": 7, "7 am.": 23, "8 am.": 15, "9 am.": 15, "10 am.": 38, "11 am.": 23, "12 pm.": 30, "1 pm.": 46, "2 pm.": 100, "3 pm.": 61, "4 pm.": 30, "5 pm.": 7, "6 pm.": 30, "7 pm.": 38, "8 pm.": 69, "9 pm.": 84, "10 pm.": 46, "11 pm.": 46, "12 am.": 46, "1 am.": 61, "2 am.": 46, "3 am.": 76}, "Thursday": {"4 am.": 7, "5 am.": 7, "6 am.": 15, "7 am.": 7, "8 am.": 0, "9 am.": 0, "10 am.": 0, "11 am.": 7, "12 pm.": 23, "1 pm.": 7, "2 pm.": 7, "3 pm.": 7, "4 pm.": 7, "5 pm.": 15, "6 pm.": 30, "7 pm.": 30, "8 pm.": 30, "9 pm.": 7, "10 pm.": 0, "11 pm.": 0, "12 am.": 0, "1 am.": 0, "2 am.": 7, "3 am.": 15}, "Friday": {"4 am.": 23, "5 am.": 30, "6 am.": 15, "7 am.": 15, "8 am.": 0, "9 am.": 0, "10 am.": 7, "11 am.": 0, "12 pm.": 7, "1 pm.": 23, "2 pm.": 7, "3 pm.": 0, "4 pm.": 0, "5 pm.": 0, "6 pm.": 0, "7 pm.": 0, "8 pm.": 7, "9 pm.": 7, "10 pm.": 7, "11 pm.": 15, "12 am.": 7, "1 am.": 0, "2 am.": 7, "3 am.": 23}, "Saturday": {"4 am.": 30, "5 am.": 7, "6 am.": 0, "7 am.": 0, "8 am.": 7, "9 am.": 15, "10 am.": 7, "11 am.": 7, "12 pm.": 15, "1 pm.": 7, "2 pm.": 0, "3 pm.": 0, "4 pm.": 7, "5 pm.": 23, "6 pm.": 7, "7 pm.": 0, "8 pm.": 0, "9 pm.": 0, "10 pm.": 0, "11 pm.": 0, "12 am.": 15, "1 am.": 38, "2 am.": 76, "3 am.": 61}, "Sunday": {"4 am.": 0, "5 am.": 0, "6 am.": 7, "7 am.": 23, "8 am.": 46, "9 am.": 53, "10 am.": 23, "11 am.": 30, "12 pm.": 38, "1 pm.": 61, "2 pm.": 23, "3 pm.": 7, "4 pm.": 0, "5 pm.": 0, "6 pm.": 0, "7 pm.": 0, "8 pm.": 0, "9 pm.": 15, "10 pm.": 30, "11 pm.": 38, "12 am.": 23, "1 am.": 30, "2 am.": 7, "3 am.": 0}}, "About": {"Accessibility": ["Wheelchair-accessible entrance"]}, "url": "https://www.google.com/maps/place/Blk+51+Playground/data=!4m7!3m6!1s0x31da1b245d92774f:0xccacdf5b83928cf3!8m2!3d1.2736822!4d103.8103107!16s%2Fg%2F11t7pdljkc!19sChIJT3eSXSQb2jER84ySg1vfrMw?authuser=0&hl=en&rclk=1", "status": "success", "place_id": "ChIJT3eSXSQb2jER84ySg1vfrMw", "timestamp": "2024-12-09 03:07:52.353585", "metadata": {"Copy address": "\ue0c8\nTelok Blangah Dr, Block 51, Singapore 100051", "Copy plus code": "\uf186\n7RF6+F4 Singapore"}}