{"Popular times": {"Monday": {"5 am.": 0, "6 am.": 9, "7 am.": 9, "8 am.": 19, "9 am.": 57, "10 am.": 71, "11 am.": 100, "12 pm.": 76, "1 pm.": 85, "2 pm.": 76, "3 pm.": 66, "4 pm.": 52, "5 pm.": 33, "6 pm.": 38, "7 pm.": 23, "8 pm.": 23, "9 pm.": 19, "10 pm.": 4}, "Tuesday": {"5 am.": 0, "6 am.": 38, "7 am.": 42, "8 am.": 28, "9 am.": 28, "10 am.": 52, "11 am.": 57, "12 pm.": 23, "1 pm.": 9, "2 pm.": 0, "3 pm.": 0, "4 pm.": 0, "5 pm.": 4, "6 pm.": 19, "7 pm.": 14, "8 pm.": 28, "9 pm.": 38, "10 pm.": 57}, "Wednesday": {"5 am.": 0, "6 am.": 0, "7 am.": 0, "8 am.": 0, "9 am.": 9, "10 am.": 9, "11 am.": 28, "12 pm.": 23, "1 pm.": 38, "2 pm.": 33, "3 pm.": 47, "4 pm.": 28, "5 pm.": 33, "6 pm.": 47, "7 pm.": 38, "8 pm.": 47, "9 pm.": 42, "10 pm.": 28}, "Thursday": {"5 am.": 0, "6 am.": 23, "7 am.": 14, "8 am.": 9, "9 am.": 19, "10 am.": 42, "11 am.": 76, "12 pm.": 80, "1 pm.": 47, "2 pm.": 42, "3 pm.": 42, "4 pm.": 66, "5 pm.": 95, "6 pm.": 80, "7 pm.": 71, "8 pm.": 38, "9 pm.": 33, "10 pm.": 47}, "Friday": {"5 am.": 0, "6 am.": 0, "7 am.": 4, "8 am.": 9, "9 am.": 4, "10 am.": 9, "11 am.": 19, "12 pm.": 47, "1 pm.": 33, "2 pm.": 28, "3 pm.": 19, "4 pm.": 28, "5 pm.": 23, "6 pm.": 33, "7 pm.": 38, "8 pm.": 47, "9 pm.": 52, "10 pm.": 57}, "Saturday": {"5 am.": 0, "6 am.": 4, "7 am.": 0, "8 am.": 9, "9 am.": 28, "10 am.": 57, "11 am.": 42, "12 pm.": 33, "1 pm.": 33, "2 pm.": 52, "3 pm.": 52, "4 pm.": 47, "5 pm.": 33, "6 pm.": 28, "7 pm.": 14, "8 pm.": 14, "9 pm.": 4, "10 pm.": 4}, "Sunday": {"5 am.": 0, "6 am.": 66, "7 am.": 47, "8 am.": 33, "9 am.": 23, "10 am.": 38, "11 am.": 76, "12 pm.": 80, "1 pm.": 61, "2 pm.": 47, "3 pm.": 52, "4 pm.": 66, "5 pm.": 47, "6 pm.": 23, "7 pm.": 19, "8 pm.": 33, "9 pm.": 52, "10 pm.": 28}}, "About": {"Accessibility": ["Wheelchair-accessible car park", "Wheelchair-accessible entrance", "Wheelchair-accessible seating", "Wheelchair-accessible toilet"], "Service options": ["Delivery", "Takeaway", "Dine-in"], "Highlights": ["Rooftop seating"], "Offerings": ["Coffee", "Halal food", "Happy-hour food", "Late-night food", "Small plates", "Vegetarian options"], "Dining options": ["Breakfast", "Lunch", "Dinner", "Catering", "Dessert", "Seating"], "Amenities": ["Toilets"], "Atmosphere": ["Casual"], "Crowd": ["Family friendly", "Groups", "LGBTQ+ friendly", "Transgender safe space"], "Planning": ["Accepts reservations"], "Children": ["Good for kids", "Kids' menu"], "Parking": ["Paid parking lot", "Plenty of parking"]}, "url": "https://www.google.com/maps/place/Mari+Mari+Seafood+-+Woodlands+Koufu+Headquarters/data=!4m7!3m6!1s0x31da138f0842e1dd:0xefe81d59b056ba41!8m2!3d1.4285618!4d103.7994018!16s%2Fg%2F11qntvg9p0!19sChIJ3eFCCI8T2jERQbpWsFkd6O8?authuser=0&hl=en&rclk=1", "status": "success", "place_id": "ChIJ3eFCCI8T2jERQbpWsFkd6O8", "timestamp": "2024-12-11 01:08:32.053295", "metadata": {"Copy address": "\ue0c8\n1 Woodlands Height, Singapore 737859", "Open reservation link": "\ue878\nFind a table\nwhatsapp.com", "Place an order": "\ue558\nPlace an order", "Copy website": "\ue14d", "Open website": "\ue80b\nfacebook.com", "Copy phone number": "\ue0b0\n9068 0033", "Call phone number": "\ue0b0", "Copy plus code": "\uf186\nCQHX+CQ Singapore"}}