{"Popular times": {}, "About": {"Accessibility": ["Wheelchair-accessible car park", "Wheelchair-accessible entrance", "Wheelchair-accessible seating", "Wheelchair-accessible toilet", "Assistive hearing loop"], "Service options": ["Delivery", "Takeaway", "Dine-in"], "Offerings": ["Halal food", "Small plates", "Vegetarian options"], "Dining options": ["Brunch", "Lunch", "Dinner", "Counter service", "Dessert", "Seating"], "Amenities": ["Toilets"], "Atmosphere": ["Casual"], "Crowd": ["Family friendly"], "Planning": ["Accepts reservations"], "Payments": ["Credit cards", "Debit cards", "NFC mobile payments", "Credit cards"], "Children": ["Good for kids", "High chairs", "Kids' menu"], "Parking": ["Paid parking lot", "Plenty of parking"], "Pets": ["Dogs allowed outside"]}, "url": "https://www.google.com/maps/place/Nuodle+%E7%89%9B%E4%B8%80%E5%98%B4+@+ARC/data=!4m7!3m6!1s0x31da1be263e7d2db:0x697dc8eac868bffc!8m2!3d1.2735194!4d103.8017593!16s%2Fg%2F11rsrg8gn1!19sChIJ29LnY-Ib2jER_L9oyOrIfWk?authuser=0&hl=en&rclk=1", "status": "success", "place_id": "ChIJ29LnY-Ib2jER_L9oyOrIfWk", "timestamp": "2024-12-10 01:37:11.312239", "metadata": {"Copy address": "\ue0c8\n460 Alexandra Rd, #01-01 Alexandra Retail Centre (ARC), Singapore 119963", "Place an order": "\ue558\nPlace an order", "Copy website": "\ue14d", "Open website": "\ue80b\ndelibowlgroup.com", "Copy phone number": "\ue0b0\n8102 7277", "Call phone number": "\ue0b0", "Copy plus code": "\uf186\n7RF2+CP Singapore"}}