{"Popular times": {}, "About": {"Service options": ["Kerbside pickup", "Delivery", "Takeaway", "Dine-in"], "Children": ["Good for kids"]}, "url": "https://www.google.com/maps/place/Almaas+Restaurant/data=!4m7!3m6!1s0x31da11905482fda3:0x1d4b0e85e6656960!8m2!3d1.3469031!4d103.7575967!16s%2Fg%2F11vt7k5lq0!19sChIJo_2CVJAR2jERYGll5oUOSx0?authuser=0&hl=en&rclk=1", "status": "success", "place_id": "ChIJo_2CVJAR2jERYGll5oUOSx0", "timestamp": "2024-12-08 15:52:25.682381", "metadata": {"Copy address": "\ue0c8\nBlk 283 Bukit Batok East Ave 3, #01-285, Singapore 650283", "Copy phone number": "\ue0b0\n8926 0917", "Call phone number": "\ue0b0", "Copy plus code": "\uf186\n8QW5+Q2 Singapore"}}