{"Popular times": {"Monday": {"6 am.": 0, "7 am.": 0, "8 am.": 0, "9 am.": 0, "10 am.": 0, "11 am.": 0, "12 pm.": 28, "1 pm.": 37, "2 pm.": 54, "3 pm.": 61, "4 pm.": 57, "5 pm.": 55, "6 pm.": 49, "7 pm.": 51, "8 pm.": 42, "9 pm.": 37, "10 pm.": 28, "11 pm.": 22, "12 am.": 11}, "Tuesday": {"6 am.": 0, "7 am.": 0, "8 am.": 0, "9 am.": 0, "10 am.": 0, "11 am.": 0, "12 pm.": 3, "1 pm.": 5, "2 pm.": 13, "3 pm.": 19, "4 pm.": 23, "5 pm.": 20, "6 pm.": 17, "7 pm.": 19, "8 pm.": 28, "9 pm.": 34, "10 pm.": 31, "11 pm.": 19, "12 am.": 12}, "Wednesday": {"6 am.": 0, "7 am.": 0, "8 am.": 0, "9 am.": 0, "10 am.": 0, "11 am.": 0, "12 pm.": 14, "1 pm.": 17, "2 pm.": 9, "3 pm.": 12, "4 pm.": 13, "5 pm.": 20, "6 pm.": 14, "7 pm.": 14, "8 pm.": 8, "9 pm.": 8, "10 pm.": 10, "11 pm.": 5, "12 am.": 5}, "Thursday": {"6 am.": 0, "7 am.": 0, "8 am.": 0, "9 am.": 0, "10 am.": 0, "11 am.": 0, "12 pm.": 20, "1 pm.": 25, "2 pm.": 22, "3 pm.": 21, "4 pm.": 15, "5 pm.": 15, "6 pm.": 22, "7 pm.": 20, "8 pm.": 22, "9 pm.": 29, "10 pm.": 29, "11 pm.": 20, "12 am.": 8}, "Friday": {"6 am.": 0, "7 am.": 0, "8 am.": 0, "9 am.": 0, "10 am.": 0, "11 am.": 0, "12 pm.": 14, "1 pm.": 15, "2 pm.": 19, "3 pm.": 33, "4 pm.": 34, "5 pm.": 34, "6 pm.": 37, "7 pm.": 43, "8 pm.": 49, "9 pm.": 45, "10 pm.": 43, "11 pm.": 45, "12 am.": 31}, "Saturday": {"6 am.": 0, "7 am.": 0, "8 am.": 0, "9 am.": 0, "10 am.": 0, "11 am.": 0, "12 pm.": 3, "1 pm.": 4, "2 pm.": 13, "3 pm.": 17, "4 pm.": 33, "5 pm.": 35, "6 pm.": 41, "7 pm.": 37, "8 pm.": 55, "9 pm.": 67, "10 pm.": 87, "11 pm.": 85, "12 am.": 68}, "Sunday": {"6 am.": 0, "7 am.": 0, "8 am.": 0, "9 am.": 0, "10 am.": 0, "11 am.": 0, "12 pm.": 14, "1 pm.": 28, "2 pm.": 35, "3 pm.": 49, "4 pm.": 53, "5 pm.": 64, "6 pm.": 68, "7 pm.": 68, "8 pm.": 65, "9 pm.": 72, "10 pm.": 84, "11 pm.": 100, "12 am.": 80, "1 am.": 52}}, "About": {"Accessibility": ["Wheelchair-accessible car park", "Wheelchair-accessible entrance", "Wheelchair-accessible seating", "Assistive hearing loop", "Wheelchair-accessible toilet"], "Service options": ["Takeaway", "Dine-in", "Delivery"], "Highlights": ["Karaoke", "Live music"], "Offerings": ["Food"], "Dining options": ["Outside food allowed", "Seating"], "Amenities": ["Wi-Fi", "Free Wi-Fi", "Toilets"], "Atmosphere": ["Casual"], "Crowd": ["Groups", "LGBTQ+ friendly", "Transgender safe space"], "Planning": ["Accepts reservations"], "Payments": ["Credit cards", "Debit cards", "NFC mobile payments", "Credit cards"], "Children": ["Good for kids"], "Parking": ["Paid parking lot", "Plenty of parking"]}, "url": "https://www.google.com/maps/place/Teo+Heng+KTV+Studio+%28White+Sands%29/data=!4m7!3m6!1s0x31da3d4c5981f349:0xfa70dbcd8ac431f!8m2!3d1.3724166!4d103.9496584!16s%2Fg%2F11tjs3zp8r!19sChIJSfOBWUw92jERH0Os2LwNpw8?authuser=0&hl=en&rclk=1", "status": "success", "place_id": "ChIJSfOBWUw92jERH0Os2LwNpw8", "timestamp": "2024-12-11 01:54:48.808435", "metadata": {"Copy address": "\ue0c8\nWhitesands, Pasir Ris Central St 3, #05-07D 1, 518457", "Copy website": "\ue14d", "Open website": "\ue80b\nktvteoheng.com.sg", "Copy phone number": "\ue0b0\n6530 3943", "Call phone number": "\ue0b0", "Copy plus code": "\uf186\n9WCX+XV Singapore"}}