{"Popular times": {}, "About": {"Children": ["Good for kids"]}, "url": "https://www.google.com/maps/place/Susan+Rojak+%26+Nasi+Lemak/data=!4m7!3m6!1s0x31da151e03df27ff:0x8dcb1877e7e73919!8m2!3d1.4460315!4d103.8287811!16s%2Fg%2F11l5xnzlp9!19sChIJ_yffAx4V2jERGTnn53cYy40?authuser=0&hl=en&rclk=1", "status": "success", "place_id": "ChIJ_yffAx4V2jERGTnn53cYy40", "timestamp": "2024-12-09 17:23:35.327698", "metadata": {"Copy address": "\ue0c8\n115 Canberra Walk, Singapore 752106", "Copy plus code": "\uf186\nCRWH+CG Singapore"}}