{"Popular times": {"Monday": {"6 am.": 0, "7 am.": 0, "8 am.": 14, "9 am.": 20, "10 am.": 26, "11 am.": 31, "12 pm.": 34, "1 pm.": 31, "2 pm.": 22, "3 pm.": 13, "4 pm.": 0, "5 pm.": 0, "6 pm.": 0, "7 pm.": 0, "8 pm.": 0, "9 pm.": 0, "10 pm.": 0, "11 pm.": 0}, "Tuesday": {}, "Wednesday": {"6 am.": 0, "7 am.": 0, "8 am.": 0, "9 am.": 22, "10 am.": 49, "11 am.": 84, "12 pm.": 100, "1 pm.": 76, "2 pm.": 45, "3 pm.": 21, "4 pm.": 0, "5 pm.": 0, "6 pm.": 0, "7 pm.": 0, "8 pm.": 0, "9 pm.": 0, "10 pm.": 0, "11 pm.": 0}, "Thursday": {"6 am.": 0, "7 am.": 0, "8 am.": 10, "9 am.": 23, "10 am.": 47, "11 am.": 80, "12 pm.": 93, "1 pm.": 72, "2 pm.": 41, "3 pm.": 18, "4 pm.": 0, "5 pm.": 0, "6 pm.": 0, "7 pm.": 0, "8 pm.": 0, "9 pm.": 0, "10 pm.": 0, "11 pm.": 0}, "Friday": {"6 am.": 0, "7 am.": 0, "8 am.": 10, "9 am.": 24, "10 am.": 51, "11 am.": 86, "12 pm.": 97, "1 pm.": 74, "2 pm.": 42, "3 pm.": 19, "4 pm.": 0, "5 pm.": 0, "6 pm.": 0, "7 pm.": 0, "8 pm.": 0, "9 pm.": 0, "10 pm.": 0, "11 pm.": 0}, "Saturday": {"6 am.": 0, "7 am.": 0, "8 am.": 11, "9 am.": 22, "10 am.": 38, "11 am.": 56, "12 pm.": 63, "1 pm.": 52, "2 pm.": 32, "3 pm.": 15, "4 pm.": 0, "5 pm.": 0, "6 pm.": 0, "7 pm.": 0, "8 pm.": 0, "9 pm.": 0, "10 pm.": 0, "11 pm.": 0}, "Sunday": {"6 am.": 0, "7 am.": 0, "8 am.": 13, "9 am.": 22, "10 am.": 29, "11 am.": 38, "12 pm.": 43, "1 pm.": 39, "2 pm.": 27, "3 pm.": 15, "4 pm.": 0, "5 pm.": 0, "6 pm.": 0, "7 pm.": 0, "8 pm.": 0, "9 pm.": 0, "10 pm.": 0, "11 pm.": 0}}, "About": {"Accessibility": ["Wheelchair-accessible entrance", "Wheelchair-accessible seating"], "Service options": ["Outdoor seating", "Delivery", "On-site services", "Takeaway", "Dine-in"], "Highlights": ["Live performances"], "Offerings": ["Alcohol", "Beer", "Coffee", "Small plates"], "Dining options": ["Breakfast", "Brunch", "Lunch", "Catering", "Dessert", "Seating"], "Amenities": ["Toilets"], "Atmosphere": ["Casual", "Cosy"], "Crowd": ["Groups"], "Planning": ["Accepts reservations"], "Payments": ["Credit cards"], "Children": ["Good for kids"], "Parking": ["Paid parking lot", "Plenty of parking"]}, "url": "https://www.google.com/maps/place/Bailey+And+Whiskey/data=!4m7!3m6!1s0x31da1bd8d75330e1:0x3d43b951b547e03b!8m2!3d1.28119!4d103.8108241!16s%2Fg%2F11rcptv1dv!19sChIJ4TBT19gb2jERO-BHtVG5Qz0?authuser=0&hl=en&rclk=1", "status": "success", "place_id": "ChIJ4TBT19gb2jERO-BHtVG5Qz0", "timestamp": "2024-12-09 07:20:18.316963", "metadata": {"Copy address": "\ue0c8\nDEPOT HEIGHTS, 108 Depot Rd, #01-30 SHOPPING CENTRE, 100108", "Copy phone number": "\ue0b0\n9325 6563", "Call phone number": "\ue0b0", "Copy plus code": "\uf186\n7RJ6+F8 Singapore"}}