{"Popular times": {"Monday": {"6 am.": 0, "7 am.": 0, "8 am.": 0, "9 am.": 0, "10 am.": 0, "11 am.": 40, "12 pm.": 61, "2 pm.": 85, "3 pm.": 85, "4 pm.": 86, "5 pm.": 87, "6 pm.": 94, "7 pm.": 88, "8 pm.": 59, "9 pm.": 30, "10 pm.": 9, "11 pm.": 0}, "Tuesday": {"6 am.": 0, "7 am.": 0, "8 am.": 0, "9 am.": 0, "10 am.": 0, "11 am.": 13, "12 pm.": 23, "1 pm.": 24, "2 pm.": 19, "3 pm.": 0, "4 pm.": 0, "5 pm.": 22, "6 pm.": 34, "7 pm.": 36, "8 pm.": 26, "9 pm.": 14, "10 pm.": 5, "11 pm.": 0}, "Wednesday": {"6 am.": 0, "7 am.": 0, "8 am.": 0, "9 am.": 0, "10 am.": 0, "11 am.": 12, "12 pm.": 23, "1 pm.": 27, "2 pm.": 25, "3 pm.": 0, "4 pm.": 0, "5 pm.": 23, "6 pm.": 42, "7 pm.": 50, "8 pm.": 40, "9 pm.": 22, "10 pm.": 7, "11 pm.": 0}, "Thursday": {"6 am.": 0, "7 am.": 0, "8 am.": 0, "9 am.": 0, "10 am.": 0, "11 am.": 26, "12 pm.": 39, "1 pm.": 39, "2 pm.": 31, "3 pm.": 0, "4 pm.": 0, "5 pm.": 27, "6 pm.": 38, "7 pm.": 39, "8 pm.": 35, "9 pm.": 21, "10 pm.": 15, "11 pm.": 0}, "Friday": {"6 am.": 0, "7 am.": 0, "8 am.": 0, "9 am.": 0, "10 am.": 0, "11 am.": 24, "12 pm.": 34, "1 pm.": 36, "2 pm.": 29, "3 pm.": 0, "4 pm.": 0, "5 pm.": 30, "6 pm.": 47, "7 pm.": 58, "8 pm.": 49, "9 pm.": 30, "10 pm.": 13, "11 pm.": 0}, "Saturday": {"6 am.": 0, "7 am.": 0, "8 am.": 0, "9 am.": 0, "10 am.": 0, "11 am.": 26, "12 pm.": 37, "1 pm.": 35, "2 pm.": 24, "3 pm.": 0, "4 pm.": 0, "5 pm.": 25, "6 pm.": 46, "7 pm.": 58, "8 pm.": 54, "9 pm.": 36, "10 pm.": 18, "11 pm.": 0}, "Sunday": {"6 am.": 0, "7 am.": 0, "8 am.": 0, "9 am.": 0, "10 am.": 0, "11 am.": 27, "12 pm.": 44, "1 pm.": 60, "2 pm.": 67, "3 pm.": 71, "4 pm.": 73, "5 pm.": 82, "6 pm.": 95, "7 pm.": 100, "8 pm.": 84, "9 pm.": 55, "10 pm.": 25, "11 pm.": 0}}, "About": {"Accessibility": ["Wheelchair-accessible car park", "Wheelchair-accessible entrance", "Wheelchair-accessible seating", "Wheelchair-accessible toilet"], "Service options": ["Takeaway", "Dine-in"], "Offerings": ["Alcohol", "Beer", "Wine"], "Dining options": ["Brunch", "Lunch", "Dinner", "Dessert", "Seating"], "Amenities": ["Toilets"], "Atmosphere": ["Casual"], "Crowd": ["Groups"], "Planning": ["Accepts reservations"], "Payments": ["Credit cards", "Debit cards", "NFC mobile payments", "Credit cards"], "Children": ["Good for kids", "High chairs"], "Parking": ["Paid parking lot", "Plenty of parking"]}, "url": "https://www.google.com/maps/place/Long+Beach+IMM/data=!4m7!3m6!1s0x31da10101550fb97:0x46e28405df46edc7!8m2!3d1.3351161!4d103.7463379!16s%2Fg%2F1tfbvzcd!19sChIJl_tQFRAQ2jERx-1G3wWE4kY?authuser=0&hl=en&rclk=1", "status": "success", "place_id": "ChIJl_tQFRAQ2jERx-1G3wWE4kY", "timestamp": "2024-12-08 13:04:55.756251", "metadata": {"Copy address": "\ue0c8\n2 Jurong East Street 21, #03-07 Next to Rooftop Garden, IMM Building, Singapore 609601", "Place an order": "\ue558\nPlace an order", "Copy website": "\ue14d", "Open website": "\ue80b\nlongbeachseafood.com.sg", "Copy phone number": "\ue0b0\n6566 9933", "Call phone number": "\ue0b0", "Copy plus code": "\uf186\n8PPW+2G Singapore"}}