{"Popular times": {}, "About": {"Service options": ["On-site services", "Takeaway", "Dine-in"], "Offerings": ["Alcohol", "Beer", "Small plates"], "Dining options": ["Lunch", "Dinner", "Catering", "Dessert"], "Amenities": ["Toilets"], "Atmosphere": ["Casual"], "Crowd": ["Groups"], "Planning": ["Accepts reservations"], "Payments": ["Cash only"], "Parking": ["Paid parking lot", "Plenty of parking"]}, "url": "https://www.google.com/maps/place/Lola+J+Kusinang+Pinoy+Restaurant+%28Filipino+Food%29/data=!4m7!3m6!1s0x31da18727dfbed85:0x359f6a34f434a15f!8m2!3d1.303884!4d103.9043973!16s%2Fg%2F1td07fyd!19sChIJhe37fXIY2jERX6E09DRqnzU?authuser=0&hl=en&rclk=1", "status": "success", "place_id": "ChIJhe37fXIY2jERX6E09DRqnzU", "timestamp": "2024-12-11 01:50:58.005790", "metadata": {"Copy address": "\ue0c8\n50 E Coast Rd, #01-80 Roxy Square 1, Singapore 428769", "Place an order": "\ue558\nPlace an order", "Copy website": "\ue14d", "Open website": "\ue80b\nfacebook.com", "Copy phone number": "\ue0b0\n9655 8875", "Call phone number": "\ue0b0", "Copy plus code": "\uf186\n8W33+HQ Singapore"}}