{"Popular times": {}, "About": {"Accessibility": ["Wheelchair-accessible car park"]}, "url": "https://www.google.com/maps/place/Sembawang+Christian+Grace+Church+Ltd/data=!4m7!3m6!1s0x31da1476ea6c3c4f:0xfa90705bcdda2d4f!8m2!3d1.426513!4d103.825912!16s%2Fg%2F11c59xxfmg!19sChIJTzxs6nYU2jERTy3azVtwkPo?authuser=0&hl=en&rclk=1", "status": "success", "place_id": "ChIJTzxs6nYU2jERTy3azVtwkPo", "timestamp": "2024-12-08 16:24:37.282490", "metadata": {"Copy address": "\ue0c8\n365 Sembawang Rd, Singapore 758380", "Copy phone number": "\ue0b0\n6754 8243", "Call phone number": "\ue0b0", "Copy plus code": "\uf186\nCRGG+J9 Singapore"}}