{"Popular times": {"Monday": {"4 am.": 7, "5 am.": 0, "6 am.": 7, "7 am.": 15, "8 am.": 7, "9 am.": 0, "10 am.": 15, "11 am.": 15, "12 pm.": 38, "1 pm.": 30, "2 pm.": 23, "3 pm.": 23, "4 pm.": 23, "5 pm.": 30, "6 pm.": 15, "7 pm.": 23, "8 pm.": 15, "9 pm.": 7, "10 pm.": 0, "11 pm.": 0, "12 am.": 0, "1 am.": 0, "2 am.": 7, "3 am.": 15}, "Tuesday": {"4 am.": 30, "5 am.": 46, "6 am.": 100, "7 am.": 69, "8 am.": 61, "9 am.": 15, "10 am.": 7, "11 am.": 15, "12 pm.": 30, "1 pm.": 23, "2 pm.": 30, "3 pm.": 15, "4 pm.": 15, "5 pm.": 0, "6 pm.": 7, "7 pm.": 23, "8 pm.": 30, "9 pm.": 46, "10 pm.": 23, "11 pm.": 7, "12 am.": 0, "1 am.": 0, "2 am.": 0, "3 am.": 7}, "Wednesday": {"4 am.": 15, "5 am.": 15, "6 am.": 38, "7 am.": 46, "8 am.": 30, "9 am.": 15, "10 am.": 0, "11 am.": 0, "12 pm.": 0, "1 pm.": 0, "2 pm.": 0, "3 pm.": 0, "4 pm.": 23, "5 pm.": 61, "6 pm.": 84, "7 pm.": 38, "8 pm.": 15, "9 pm.": 7, "10 pm.": 23, "11 pm.": 53, "12 am.": 69, "1 am.": 46, "2 am.": 30, "3 am.": 15}, "Thursday": {"4 am.": 23, "5 am.": 15, "6 am.": 15, "7 am.": 38, "8 am.": 30, "9 am.": 15, "10 am.": 0, "11 am.": 0, "12 pm.": 0, "1 pm.": 23, "2 pm.": 61, "3 pm.": 84, "4 pm.": 53, "5 pm.": 46, "6 pm.": 69, "7 pm.": 30, "8 pm.": 23, "9 pm.": 15, "10 pm.": 38, "11 pm.": 30, "12 am.": 46, "1 am.": 15, "2 am.": 15, "3 am.": 7}, "Friday": {"4 am.": 46, "5 am.": 92, "6 am.": 53, "7 am.": 23, "8 am.": 7, "9 am.": 23, "10 am.": 61, "11 am.": 38, "12 pm.": 38, "1 pm.": 15, "2 pm.": 7, "3 pm.": 0, "4 pm.": 7, "5 pm.": 15, "6 pm.": 46, "7 pm.": 38, "8 pm.": 30, "9 pm.": 7, "10 pm.": 7, "11 pm.": 23, "12 am.": 15, "1 am.": 23, "2 am.": 30, "3 am.": 30}, "Saturday": {"4 am.": 7, "5 am.": 0, "6 am.": 7, "7 am.": 15, "8 am.": 7, "9 am.": 0, "10 am.": 23, "11 am.": 53, "12 pm.": 76, "1 pm.": 53, "2 pm.": 23, "3 pm.": 0, "4 pm.": 0, "5 pm.": 0, "6 pm.": 0, "7 pm.": 0, "8 pm.": 0, "9 pm.": 0, "10 pm.": 0, "11 pm.": 15, "12 am.": 30, "1 am.": 46, "2 am.": 15, "3 am.": 7}, "Sunday": {"4 am.": 15, "5 am.": 7, "6 am.": 0, "7 am.": 7, "8 am.": 30, "9 am.": 61, "10 am.": 76, "11 am.": 53, "12 pm.": 46, "1 pm.": 61, "2 pm.": 30, "3 pm.": 15, "4 pm.": 0, "5 pm.": 15, "6 pm.": 46, "7 pm.": 53, "8 pm.": 23, "9 pm.": 7, "10 pm.": 0, "11 pm.": 15, "12 am.": 15, "1 am.": 30, "2 am.": 15, "3 am.": 15}}, "About": {"Accessibility": ["Wheelchair-accessible entrance"]}, "url": "https://www.google.com/maps/place/Duck%E2%80%99s+Nest+Playground/data=!4m7!3m6!1s0x31da3d7e60cc5851:0xdf06cc62593f99d!8m2!3d1.3649748!4d103.9532208!16s%2Fg%2F11fjtyj_3l!19sChIJUVjMYH492jERnfmTJcZs8A0?authuser=0&hl=en&rclk=1", "status": "success", "place_id": "ChIJUVjMYH492jERnfmTJcZs8A0", "timestamp": "2024-12-08 12:06:15.525942", "metadata": {"Copy plus code": "\uf186\n9X73+X7 Singapore"}}