{"Popular times": {}, "About": {"Accessibility": ["Wheelchair-accessible car park"], "Service options": ["Takeaway"], "Offerings": ["Small plates"], "Dining options": ["Brunch", "Lunch", "Dinner"], "Atmosphere": ["Casual"], "Crowd": ["Groups"], "Children": ["Good for kids"]}, "url": "https://www.google.com/maps/place/Fat+Fat+Food/data=!4m7!3m6!1s0x31da3df50dbc4ab9:0x1e35fe056bb62a11!8m2!3d1.3538247!4d103.9396749!16s%2Fg%2F11t0vpyd4l!19sChIJuUq8DfU92jERESq2awX-NR4?authuser=0&hl=en&rclk=1", "status": "success", "place_id": "ChIJuUq8DfU92jERESq2awX-NR4", "timestamp": "2024-12-08 14:26:21.190148", "metadata": {"Copy address": "\ue0c8\nOur Tampines Hub Hawker Centre #01-66, 528523", "Copy phone number": "\ue0b0\n9021 8211", "Call phone number": "\ue0b0", "Copy plus code": "\uf186\n9W3Q+GW Singapore"}}