{"Popular times": {"Monday": {"6 am.": 0, "7 am.": 0, "8 am.": 0, "9 am.": 0, "10 am.": 0, "11 am.": 25, "12 pm.": 56, "1 pm.": 61, "2 pm.": 43, "3 pm.": 20, "4 pm.": 12, "5 pm.": 17, "6 pm.": 43, "7 pm.": 33, "8 pm.": 33, "9 pm.": 17, "10 pm.": 0, "11 pm.": 0}, "Tuesday": {"6 am.": 0, "7 am.": 0, "8 am.": 0, "9 am.": 0, "10 am.": 0, "11 am.": 15, "12 pm.": 20, "1 pm.": 15, "2 pm.": 17, "3 pm.": 28, "4 pm.": 12, "5 pm.": 15, "6 pm.": 25, "7 pm.": 53, "8 pm.": 38, "9 pm.": 17, "10 pm.": 0, "11 pm.": 0}, "Wednesday": {"6 am.": 0, "7 am.": 0, "8 am.": 0, "9 am.": 0, "10 am.": 0, "11 am.": 2, "12 pm.": 0, "1 pm.": 15, "2 pm.": 30, "3 pm.": 64, "4 pm.": 35, "5 pm.": 28, "6 pm.": 7, "7 pm.": 15, "8 pm.": 33, "9 pm.": 64, "10 pm.": 0, "11 pm.": 0}, "Thursday": {"6 am.": 0, "7 am.": 0, "8 am.": 0, "9 am.": 0, "10 am.": 0, "11 am.": 7, "12 pm.": 17, "1 pm.": 30, "2 pm.": 25, "3 pm.": 28, "4 pm.": 43, "5 pm.": 41, "6 pm.": 43, "7 pm.": 66, "8 pm.": 43, "9 pm.": 30, "10 pm.": 0, "11 pm.": 0}, "Friday": {"6 am.": 0, "7 am.": 0, "8 am.": 0, "9 am.": 0, "10 am.": 0, "11 am.": 12, "12 pm.": 5, "1 pm.": 2, "2 pm.": 0, "3 pm.": 0, "4 pm.": 5, "5 pm.": 12, "6 pm.": 20, "7 pm.": 20, "8 pm.": 38, "9 pm.": 28, "10 pm.": 0, "11 pm.": 0}, "Saturday": {"6 am.": 0, "7 am.": 0, "8 am.": 0, "9 am.": 0, "10 am.": 0, "11 am.": 33, "12 pm.": 56, "1 pm.": 43, "2 pm.": 53, "3 pm.": 61, "4 pm.": 64, "5 pm.": 92, "6 pm.": 97, "7 pm.": 74, "8 pm.": 53, "9 pm.": 43, "10 pm.": 0, "11 pm.": 0}, "Sunday": {"6 am.": 0, "7 am.": 0, "8 am.": 0, "9 am.": 0, "10 am.": 0, "11 am.": 43, "12 pm.": 30, "1 pm.": 33, "2 pm.": 33, "3 pm.": 51, "4 pm.": 84, "5 pm.": 84, "6 pm.": 100, "7 pm.": 61, "8 pm.": 56, "9 pm.": 64, "10 pm.": 0, "11 pm.": 0}}, "About": {"Accessibility": ["Wheelchair-accessible car park", "Wheelchair-accessible entrance"], "Service options": ["In-store pick-up", "On-site services", "Same-day delivery"], "Payments": ["Credit cards", "NFC mobile payments"]}, "url": "https://www.google.com/maps/place/Nike/data=!4m7!3m6!1s0x31da19af03c3a2ed:0xd427ec77a707f7d6!8m2!3d1.2933752!4d103.8575243!16s%2Fg%2F1tdrtvnv!19sChIJ7aLDA68Z2jER1vcHp3fsJ9Q?authuser=0&hl=en&rclk=1", "status": "success", "place_id": "ChIJ7aLDA68Z2jER1vcHp3fsJ9Q", "timestamp": "2024-12-09 09:48:56.944455", "metadata": {"Copy address": "\ue0c8\n3 Temasek Blvd, #01-375 / 376 / 377, Singapore 038983", "Copy website": "\ue14d", "Open website": "\ue80b\nnike.com", "Copy phone number": "\ue0b0\n6837 0871", "Call phone number": "\ue0b0", "Copy plus code": "\uf186\n7VV5+92 Singapore"}}