{"Popular times": {}, "About": {"Accessibility": ["Wheelchair-accessible car park", "Wheelchair-accessible entrance"], "Service options": ["On-site services"]}, "url": "https://www.google.com/maps/place/Ramakrishna+Mission/data=!4m7!3m6!1s0x31da1797f1a23e35:0x54343b751f9c877b!8m2!3d1.3440699!4d103.880249!16s%2Fg%2F11b6dp4jj5!19sChIJNT6i8ZcX2jERe4ecH3U7NFQ?authuser=0&hl=en&rclk=1", "status": "success", "place_id": "ChIJNT6i8ZcX2jERe4ecH3U7NFQ", "timestamp": "2024-12-10 01:32:28.528674", "metadata": {"Copy address": "\ue0c8\n179 Bartley Rd, Singapore 539784", "Copy website": "\ue14d", "Open website": "\ue80b\nramakrishna.org.sg", "Copy phone number": "\ue0b0\n6288 9077", "Call phone number": "\ue0b0", "Copy plus code": "\uf186\n8VVH+CQ Singapore"}}