{"Popular times": {"Monday": {"6 am.": 0, "7 am.": 0, "8 am.": 0, "9 am.": 0, "10 am.": 0, "11 am.": 0, "12 pm.": 0, "1 pm.": 17, "2 pm.": 26, "3 pm.": 17, "4 pm.": 20, "5 pm.": 24, "6 pm.": 35, "7 pm.": 44, "8 pm.": 41, "9 pm.": 30, "10 pm.": 21, "11 pm.": 16}, "Tuesday": {"6 am.": 0, "7 am.": 0, "8 am.": 0, "9 am.": 0, "10 am.": 0, "11 am.": 14, "12 pm.": 25, "1 pm.": 13, "2 pm.": 12, "3 pm.": 8, "4 pm.": 24, "5 pm.": 32, "6 pm.": 56, "7 pm.": 52, "8 pm.": 51, "9 pm.": 40, "10 pm.": 40, "11 pm.": 29, "12 am.": 28, "1 am.": 14, "2 am.": 8}, "Wednesday": {"6 am.": 0, "7 am.": 0, "8 am.": 0, "9 am.": 0, "10 am.": 0, "11 am.": 55, "12 pm.": 75, "1 pm.": 66, "2 pm.": 48, "3 pm.": 32, "4 pm.": 36, "5 pm.": 38, "6 pm.": 44, "7 pm.": 42, "8 pm.": 41, "9 pm.": 53, "10 pm.": 58, "11 pm.": 48, "12 am.": 26, "1 am.": 10}, "Thursday": {"6 am.": 0, "7 am.": 0, "8 am.": 0, "9 am.": 0, "10 am.": 0, "11 am.": 50, "12 pm.": 68, "1 pm.": 60, "2 pm.": 44, "3 pm.": 40, "4 pm.": 37, "5 pm.": 48, "6 pm.": 62, "7 pm.": 72, "8 pm.": 72, "9 pm.": 63, "10 pm.": 61, "11 pm.": 49, "12 am.": 32, "1 am.": 12, "2 am.": 4}, "Friday": {"6 am.": 0, "7 am.": 0, "8 am.": 0, "9 am.": 0, "10 am.": 0, "11 am.": 40, "12 pm.": 45, "1 pm.": 41, "2 pm.": 37, "3 pm.": 32, "4 pm.": 17, "5 pm.": 14, "6 pm.": 23, "7 pm.": 32, "8 pm.": 52, "9 pm.": 67, "10 pm.": 77, "11 pm.": 70, "12 am.": 53, "1 am.": 32, "2 am.": 20}, "Saturday": {"6 am.": 0, "7 am.": 0, "8 am.": 0, "9 am.": 0, "10 am.": 0, "11 am.": 35, "12 pm.": 50, "1 pm.": 62, "2 pm.": 50, "3 pm.": 43, "4 pm.": 37, "5 pm.": 28, "6 pm.": 37, "7 pm.": 60, "8 pm.": 78, "9 pm.": 96, "10 pm.": 95, "11 pm.": 100, "12 am.": 69, "1 am.": 52, "2 am.": 28}, "Sunday": {"6 am.": 0, "7 am.": 0, "8 am.": 0, "9 am.": 0, "10 am.": 0, "11 am.": 29, "12 pm.": 43, "1 pm.": 36, "2 pm.": 24, "3 pm.": 15, "4 pm.": 22, "5 pm.": 30, "6 pm.": 41, "7 pm.": 38, "8 pm.": 40, "9 pm.": 48, "10 pm.": 76, "11 pm.": 63, "12 am.": 43, "1 am.": 16, "2 am.": 7}}, "About": {"Accessibility": ["Wheelchair-accessible entrance", "Wheelchair-accessible seating"], "From the business": ["Identifies as women-owned"], "Service options": ["Outdoor seating", "No-contact delivery", "Delivery", "Takeaway", "Dine-in"], "Offerings": ["Alcohol", "Beer", "Cocktails", "Coffee", "Happy-hour drinks", "Late-night food", "Small plates", "Spirits", "Vegetarian options", "Wine"], "Dining options": ["Brunch", "Lunch", "Dinner", "Dessert", "Seating"], "Amenities": ["Bar on site", "Gender-neutral toilets", "Toilets", "Wi-Fi", "Free Wi-Fi"], "Atmosphere": ["Casual"], "Crowd": ["Family friendly", "Groups"], "Planning": ["Accepts reservations"], "Payments": ["Cash only", "Credit cards", "Debit cards", "NFC mobile payments", "Credit cards"], "Children": ["Good for kids", "High chairs"], "Pets": ["Dogs allowed", "Dogs allowed outside"]}, "url": "https://www.google.com/maps/place/Bluemist+Restaurant/data=!4m7!3m6!1s0x31da196b5f6ea63f:0x96002c659a3d366f!8m2!3d1.2769734!4d103.8432784!16s%2Fg%2F1tdx1nf4!19sChIJP6ZuX2sZ2jERbzY9mmUsAJY?authuser=0&hl=en&rclk=1", "status": "success", "place_id": "ChIJP6ZuX2sZ2jERbzY9mmUsAJY", "timestamp": "2024-12-11 02:33:52.451075", "metadata": {"Copy address": "\ue0c8\nBlk 7 Tanjong Pagar Plz, #01-103, Singapore 081007", "Place an order": "\ue558\nPlace an order", "Copy menu link": "\ue14d", "Open menu link": "\ue561\nMenu\nbluemist.sg", "Copy website": "\ue14d", "Open website": "\ue80b\nbluemist.sg", "Copy phone number": "\ue0b0\n6220 1820", "Call phone number": "\ue0b0", "Copy plus code": "\uf186\n7RGV+Q8 Singapore"}}