{"Popular times": {}, "About": {"Accessibility": ["Wheelchair-accessible entrance", "Wheelchair-accessible seating", "Wheelchair-accessible toilet", "Wheelchair-accessible car park"], "From the business": ["Identifies as women-owned"], "Service options": ["Outdoor seating", "On-site services", "Takeaway", "Dine-in", "Delivery"], "Offerings": ["Coffee", "Prepared foods", "Small plates", "Vegetarian options"], "Dining options": ["Breakfast", "Lunch", "Dessert", "Seating"], "Amenities": ["Gender-neutral toilets", "Toilets"], "Atmosphere": ["Casual", "Cosy"], "Planning": ["Accepts reservations"], "Payments": ["Credit cards", "Debit cards", "NFC mobile payments", "Credit cards"]}, "url": "https://www.google.com/maps/place/KY%C5%8C+KOHEE+112+Robinson/data=!4m7!3m6!1s0x31da19cf6874f325:0x1961f74c6b3f9757!8m2!3d1.2792727!4d103.8488065!16s%2Fg%2F11rmn8935m!19sChIJJfN0aM8Z2jERV5c_a0z3YRk?authuser=0&hl=en&rclk=1", "status": "success", "place_id": "ChIJJfN0aM8Z2jERV5c_a0z3YRk", "timestamp": "2024-12-09 04:38:53.195147", "metadata": {"Copy address": "\ue0c8\n112 Robinson Rd, #01-01, Singapore 068902", "Open reservation link": "\ue878\nFind a table\nquandoo.sg", "See items for sale here": "Search items at this store", "Copy menu link": "\ue14d", "Open menu link": "\ue561\nMenu\nkyokohee.com", "Copy website": "\ue14d", "Open website": "\ue80b\nkyokohee.com", "Copy plus code": "\uf186\n7RHX+PG Singapore"}}