{"Popular times": {"Monday": {"6 am.": 0, "7 am.": 0, "8 am.": 0, "9 am.": 0, "10 am.": 54, "11 am.": 34, "12 pm.": 31, "1 pm.": 11, "2 pm.": 14, "3 pm.": 31, "4 pm.": 51, "5 pm.": 91, "6 pm.": 85, "7 pm.": 51, "8 pm.": 17, "9 pm.": 14, "10 pm.": 0, "11 pm.": 0}, "Tuesday": {"6 am.": 0, "7 am.": 0, "8 am.": 0, "9 am.": 0, "10 am.": 0, "11 am.": 37, "12 pm.": 20, "1 pm.": 25, "2 pm.": 31, "3 pm.": 57, "4 pm.": 45, "5 pm.": 28, "6 pm.": 25, "7 pm.": 31, "8 pm.": 25, "9 pm.": 37, "10 pm.": 0, "11 pm.": 0}, "Wednesday": {"6 am.": 0, "7 am.": 0, "8 am.": 0, "9 am.": 0, "10 am.": 0, "11 am.": 8, "12 pm.": 17, "1 pm.": 31, "2 pm.": 45, "3 pm.": 34, "4 pm.": 31, "5 pm.": 31, "6 pm.": 48, "7 pm.": 85, "8 pm.": 42, "9 pm.": 20, "10 pm.": 0, "11 pm.": 0}, "Thursday": {"6 am.": 0, "7 am.": 0, "8 am.": 0, "9 am.": 0, "10 am.": 0, "11 am.": 65, "12 pm.": 68, "1 pm.": 57, "2 pm.": 57, "3 pm.": 45, "4 pm.": 31, "5 pm.": 34, "6 pm.": 22, "7 pm.": 25, "8 pm.": 17, "9 pm.": 20, "10 pm.": 0, "11 pm.": 0}, "Friday": {"6 am.": 0, "7 am.": 0, "8 am.": 0, "9 am.": 0, "10 am.": 0, "11 am.": 25, "12 pm.": 40, "1 pm.": 40, "2 pm.": 48, "3 pm.": 42, "4 pm.": 20, "5 pm.": 8, "6 pm.": 20, "7 pm.": 51, "8 pm.": 80, "9 pm.": 80, "10 pm.": 0, "11 pm.": 0}, "Saturday": {"6 am.": 0, "7 am.": 0, "8 am.": 0, "9 am.": 0, "10 am.": 0, "11 am.": 77, "12 pm.": 34, "1 pm.": 28, "2 pm.": 40, "3 pm.": 51, "4 pm.": 31, "5 pm.": 42, "6 pm.": 40, "7 pm.": 74, "8 pm.": 62, "9 pm.": 54, "10 pm.": 0, "11 pm.": 0}, "Sunday": {"6 am.": 0, "7 am.": 0, "8 am.": 0, "9 am.": 0, "10 am.": 40, "11 am.": 42, "12 pm.": 31, "1 pm.": 28, "2 pm.": 42, "3 pm.": 48, "4 pm.": 68, "5 pm.": 94, "6 pm.": 100, "7 pm.": 88, "8 pm.": 62, "9 pm.": 28, "10 pm.": 0, "11 pm.": 0}}, "About": {"Accessibility": ["Wheelchair-accessible car park", "Wheelchair-accessible entrance", "Wheelchair-accessible seating", "Wheelchair-accessible toilet"], "Service options": ["No-contact delivery", "Delivery", "On-site services", "Takeaway", "Dine-in"], "Offerings": ["Coffee", "Small plates"], "Dining options": ["Breakfast", "Brunch", "Lunch", "Dinner", "Dessert", "Seating"], "Amenities": ["Toilets"], "Atmosphere": ["Casual"], "Crowd": ["Groups"], "Planning": ["Accepts reservations"], "Payments": ["Credit cards", "Debit cards", "NFC mobile payments", "Credit cards"], "Children": ["Good for kids"]}, "url": "https://www.google.com/maps/place/Tim+Ho+Wan/data=!4m7!3m6!1s0x31da1505be0e8c3b:0xdc9d57bc62e05182!8m2!3d1.4064412!4d103.9020846!16s%2Fg%2F11flbsbsvb!19sChIJO4wOvgUV2jERglHgYrxXndw?authuser=0&hl=en&rclk=1", "status": "success", "place_id": "ChIJO4wOvgUV2jERglHgYrxXndw", "timestamp": "2024-12-09 23:29:33.050837", "metadata": {"Copy address": "\ue0c8\n83 Punggol Central, #01-62 Waterway Point West Wing, Singapore 828761", "Place an order": "\ue558\nPlace an order", "Copy website": "\ue14d", "Open website": "\ue80b\ntimhowan.com", "Copy phone number": "\ue0b0\n6243 7088", "Call phone number": "\ue0b0", "Copy plus code": "\uf186\nCW42+HR Singapore"}}