{"Popular times": {"Monday": {"5 am.": 0, "6 am.": 6, "7 am.": 10, "8 am.": 19, "9 am.": 29, "10 am.": 36, "11 am.": 37, "12 pm.": 36, "1 pm.": 32, "2 pm.": 27, "3 pm.": 22, "4 pm.": 19, "5 pm.": 24, "6 pm.": 32, "7 pm.": 36, "8 pm.": 33, "9 pm.": 21, "10 pm.": 10}, "Tuesday": {"5 am.": 0, "6 am.": 6, "7 am.": 12, "8 am.": 18, "9 am.": 26, "10 am.": 40, "11 am.": 66, "12 pm.": 87, "1 pm.": 76, "2 pm.": 46, "3 pm.": 25, "4 pm.": 15, "5 pm.": 17, "6 pm.": 24, "7 pm.": 30, "8 pm.": 25, "9 pm.": 19, "10 pm.": 10}, "Wednesday": {"5 am.": 0, "6 am.": 5, "7 am.": 7, "8 am.": 13, "9 am.": 23, "10 am.": 45, "11 am.": 79, "12 pm.": 100, "1 pm.": 80, "2 pm.": 46, "3 pm.": 21, "4 pm.": 17, "5 pm.": 18, "6 pm.": 26, "7 pm.": 27, "8 pm.": 25, "9 pm.": 17, "10 pm.": 11}, "Thursday": {"5 am.": 0, "6 am.": 8, "7 am.": 15, "8 am.": 19, "9 am.": 29, "10 am.": 48, "11 am.": 72, "12 pm.": 87, "1 pm.": 72, "2 pm.": 46, "3 pm.": 29, "4 pm.": 22, "5 pm.": 25, "6 pm.": 31, "7 pm.": 31, "8 pm.": 23, "9 pm.": 12, "10 pm.": 6}, "Friday": {"5 am.": 0, "6 am.": 7, "7 am.": 10, "8 am.": 14, "9 am.": 21, "10 am.": 40, "11 am.": 69, "12 pm.": 88, "1 pm.": 73, "2 pm.": 45, "3 pm.": 27, "4 pm.": 23, "5 pm.": 26, "6 pm.": 30, "7 pm.": 30, "8 pm.": 25, "9 pm.": 17, "10 pm.": 8}, "Saturday": {"5 am.": 0, "6 am.": 5, "7 am.": 9, "8 am.": 16, "9 am.": 24, "10 am.": 35, "11 am.": 48, "12 pm.": 58, "1 pm.": 49, "2 pm.": 37, "3 pm.": 25, "4 pm.": 22, "5 pm.": 23, "6 pm.": 24, "7 pm.": 25, "8 pm.": 20, "9 pm.": 14, "10 pm.": 8}, "Sunday": {"5 am.": 0, "6 am.": 8, "7 am.": 18, "8 am.": 28, "9 am.": 33, "10 am.": 33, "11 am.": 31, "12 pm.": 31, "1 pm.": 28, "2 pm.": 21, "3 pm.": 18, "4 pm.": 17, "5 pm.": 20, "6 pm.": 27, "7 pm.": 30, "8 pm.": 27, "9 pm.": 20, "10 pm.": 12}}, "About": {"Accessibility": ["Wheelchair-accessible entrance", "Wheelchair-accessible seating"], "Service options": ["Outdoor seating", "Takeaway", "Dine-in"], "Offerings": ["Alcohol", "Beer", "Coffee", "Small plates"], "Dining options": ["Breakfast", "Brunch", "Lunch", "Dinner", "Seating"], "Amenities": ["Toilets"], "Atmosphere": ["Casual"], "Crowd": ["Groups"], "Planning": ["Accepts reservations"], "Children": ["Good for kids"]}, "url": "https://www.google.com/maps/place/6+@+Holland+Coffeeshop/data=!4m7!3m6!1s0x31da1bcd77f8b33b:0x11e35e8de93796d6!8m2!3d1.3071882!4d103.7952664!16s%2Fg%2F11f64c1bk7!19sChIJO7P4d80b2jER1pY36Y1e4xE?authuser=0&hl=en&rclk=1", "status": "success", "place_id": "ChIJO7P4d80b2jER1pY36Y1e4xE", "timestamp": "2024-12-12 21:59:09.538536", "metadata": {"Copy address": "\ue0c8\n6 Holland Cl, Block 6, Singapore 271006", "Copy plus code": "\uf186\n8Q4W+V4 Singapore"}}