{"Popular times": {}, "About": {"Accessibility": ["Wheelchair-accessible car park", "Wheelchair-accessible entrance", "Wheelchair-accessible seating", "Wheelchair-accessible toilet"]}, "url": "https://www.google.com/maps/place/Pei+Tong+Primary+School/data=!4m7!3m6!1s0x31da1a84b222873d:0xccb2a0c9cb175334!8m2!3d1.3161197!4d103.7675906!16s%2Fm%2F02vk93p!19sChIJPYcisoQa2jERNFMXy8mgssw?authuser=0&hl=en&rclk=1", "status": "success", "place_id": "ChIJPYcisoQa2jERNFMXy8mgssw", "timestamp": "2024-12-09 02:45:16.947604", "metadata": {"Copy address": "\ue0c8\n15 Clementi Ave 5, Singapore 129857", "Copy website": "\ue14d", "Open website": "\ue80b\npeitongpri.moe.edu.sg", "Copy phone number": "\ue0b0\n6777 5458", "Call phone number": "\ue0b0", "Copy plus code": "\uf186\n8Q89+C2 Singapore"}}