{"Popular times": {"Monday": {"6 am.": 0, "7 am.": 0, "8 am.": 0, "9 am.": 16, "10 am.": 27, "11 am.": 39, "12 pm.": 45, "1 pm.": 45, "2 pm.": 47, "4 pm.": 41, "5 pm.": 34, "6 pm.": 0, "7 pm.": 0, "8 pm.": 0, "9 pm.": 0, "10 pm.": 0, "11 pm.": 0}, "Tuesday": {}, "Wednesday": {"6 am.": 0, "7 am.": 0, "8 am.": 0, "9 am.": 4, "10 am.": 11, "11 am.": 32, "12 pm.": 51, "1 pm.": 66, "2 pm.": 70, "3 pm.": 64, "4 pm.": 52, "5 pm.": 35, "6 pm.": 0, "7 pm.": 0, "8 pm.": 0, "9 pm.": 0, "10 pm.": 0, "11 pm.": 0}, "Thursday": {"6 am.": 0, "7 am.": 0, "8 am.": 0, "9 am.": 35, "10 am.": 45, "11 am.": 47, "12 pm.": 48, "1 pm.": 52, "2 pm.": 46, "3 pm.": 40, "4 pm.": 27, "5 pm.": 17, "6 pm.": 0, "7 pm.": 0, "8 pm.": 0, "9 pm.": 0, "10 pm.": 0, "11 pm.": 0}, "Friday": {"6 am.": 0, "7 am.": 0, "8 am.": 0, "9 am.": 29, "10 am.": 39, "11 am.": 51, "12 pm.": 58, "1 pm.": 63, "2 pm.": 64, "3 pm.": 66, "4 pm.": 63, "5 pm.": 52, "6 pm.": 0, "7 pm.": 0, "8 pm.": 0, "9 pm.": 0, "10 pm.": 0, "11 pm.": 0}, "Saturday": {"6 am.": 0, "7 am.": 0, "8 am.": 0, "9 am.": 63, "10 am.": 91, "11 am.": 100, "12 pm.": 96, "1 pm.": 76, "2 pm.": 61, "3 pm.": 51, "4 pm.": 39, "5 pm.": 23, "6 pm.": 0, "7 pm.": 0, "8 pm.": 0, "9 pm.": 0, "10 pm.": 0, "11 pm.": 0}, "Sunday": {"6 am.": 0, "7 am.": 0, "8 am.": 0, "9 am.": 39, "10 am.": 59, "11 am.": 61, "12 pm.": 64, "1 pm.": 53, "2 pm.": 51, "3 pm.": 48, "4 pm.": 42, "5 pm.": 33, "6 pm.": 0, "7 pm.": 0, "8 pm.": 0, "9 pm.": 0, "10 pm.": 0, "11 pm.": 0}}, "About": {"Accessibility": ["Wheelchair-accessible car park", "Wheelchair-accessible entrance", "Wheelchair-accessible toilet"], "Amenities": ["Restaurant", "Toilets"], "Children": ["Good for kids"]}, "url": "https://www.google.com/maps/place/Changi+Chapel+%26+Museum/data=!4m7!3m6!1s0x31da3cf7eac10109:0x8ece052eb785a8ab!8m2!3d1.362212!4d103.974025!16s%2Fm%2F03hnk16!19sChIJCQHB6vc82jERq6iFty4Fzo4?authuser=0&hl=en&rclk=1", "status": "success", "place_id": "ChIJCQHB6vc82jERq6iFty4Fzo4", "timestamp": "2024-12-08 15:52:54.676323", "metadata": {"Copy address": "\ue0c8\n1000 Upper Changi Rd N, Singapore 507707", "Copy website": "\ue14d", "Open website": "\ue80b\nnhb.gov.sg", "Copy phone number": "\ue0b0\n6242 6033", "Call phone number": "\ue0b0", "Copy plus code": "\uf186\n9X6F+VJ Singapore"}}