{"Popular times": {}, "About": {"Accessibility": ["Wheelchair-accessible car park", "Wheelchair-accessible entrance"]}, "url": "https://www.google.com/maps/place/East+Asia+Institute+of+Management/data=!4m7!3m6!1s0x31da17606abdea9d:0x7e63ef7c5be80206!8m2!3d1.3280597!4d103.8456344!16s%2Fg%2F155stc0v!19sChIJneq9amAX2jERBgLoW3zvY34?authuser=0&hl=en&rclk=1", "status": "success", "place_id": "ChIJneq9amAX2jERBgLoW3zvY34", "timestamp": "2024-12-08 13:58:28.944402", "metadata": {"Copy address": "\ue0c8\n9 Ah Hood Rd, Singapore 329975", "Copy website": "\ue14d", "Open website": "\ue80b\neaim.edu.sg", "Copy phone number": "\ue0b0\n6252 5500", "Call phone number": "\ue0b0", "Copy plus code": "\uf186\n8RHW+67 Singapore"}}