{"Popular times": {}, "About": {"Accessibility": ["Wheelchair-accessible car park", "Wheelchair-accessible entrance"], "Service options": ["Online classes", "On-site services"]}, "url": "https://www.google.com/maps/place/Berries+World+of+Learning+School+%28Bishan+St+12%29/data=!4m7!3m6!1s0x31da17148a287949:0xc0afb34cdd9f467f!8m2!3d1.3473362!4d103.8494819!16s%2Fg%2F11b6rzzzz4!19sChIJSXkoihQX2jERf0af3Uyzr8A?authuser=0&hl=en&rclk=1", "status": "success", "place_id": "ChIJSXkoihQX2jERf0af3Uyzr8A", "timestamp": "2024-12-09 12:22:12.318309", "metadata": {"Copy address": "\ue0c8\n116 Bishan St 12, #01-26, Singapore 570116", "Copy website": "\ue14d", "Open website": "\ue80b\nberriesworld.com", "Copy phone number": "\ue0b0\n6554 1729", "Call phone number": "\ue0b0", "Copy plus code": "\uf186\n8RWX+WQ Singapore"}}