{"Popular times": {}, "About": {"Accessibility": ["Wheelchair-accessible car park", "Wheelchair-accessible entrance", "Wheelchair-accessible seating"], "Service options": ["Takeaway", "Dine-in"], "Offerings": ["Coffee", "Small plates"], "Dining options": ["Breakfast", "Brunch", "Lunch", "Dinner", "Seating"], "Amenities": ["Toilets"], "Atmosphere": ["Casual"], "Crowd": ["Family friendly"], "Children": ["Good for kids"]}, "url": "https://www.google.com/maps/place/Kopitiam+Corner+@+Pasir+Ris+Costa+Ris/data=!4m7!3m6!1s0x31da3d6a19cfce0b:0xad394366f6d42c9f!8m2!3d1.3695607!4d103.9477517!16s%2Fg%2F11g1p_mnp0!19sChIJC87PGWo92jERnyzU9mZDOa0?authuser=0&hl=en&rclk=1", "status": "success", "place_id": "ChIJC87PGWo92jERnyzU9mZDOa0", "timestamp": "2024-12-12 19:29:27.444740", "metadata": {"Copy address": "\ue0c8\n527C Pasir Ris Street 51, #01-01, Singapore 513527", "Copy website": "\ue14d", "Open website": "\ue80b\nkopitiam.biz", "Copy plus code": "\uf186\n9W9X+R4 Singapore"}}