{"Popular times": {}, "About": {"Accessibility": ["Wheelchair-accessible entrance"], "Children": ["Good for kids"]}, "url": "https://www.google.com/maps/place/Oasis+@+Mulberry+Park/data=!4m7!3m6!1s0x31da1785a1acadc1:0xf505a9b0b108678!8m2!3d1.3320596!4d103.8785996!16s%2Fg%2F11g6l_s0ss!19sChIJwa2soYUX2jEReIYQC5taUA8?authuser=0&hl=en&rclk=1", "status": "success", "place_id": "ChIJwa2soYUX2jEReIYQC5taUA8", "timestamp": "2024-12-11 00:53:36.412989", "metadata": {"Copy address": "\ue0c8\nMulberry Ave", "Copy phone number": "\ue0b0\n9004 3078", "Call phone number": "\ue0b0", "Copy plus code": "\uf186\n8VJH+RC Singapore"}}