{"Popular times": {}, "About": {"Accessibility": ["Wheelchair-accessible car park", "Wheelchair-accessible entrance"], "Service options": ["Takeaway", "Dine-in"]}, "url": "https://www.google.com/maps/place/What+The+Fish/data=!4m7!3m6!1s0x31da11c83f3421b1:0x2024cef168b734c4!8m2!3d1.3330166!4d103.7437038!16s%2Fg%2F11v48v70gx!19sChIJsSE0P8gR2jERxDS3aPHOJCA?authuser=0&hl=en&rclk=1", "status": "success", "place_id": "ChIJsSE0P8gR2jERxDS3aPHOJCA", "timestamp": "2024-12-08 17:02:45.794162", "metadata": {"Copy address": "\ue0c8\n50 Jurong Gateway Rd, Singapore 608549", "Place an order": "\ue558\nPlace an order", "Copy website": "\ue14d", "Open website": "\ue80b\nwhatthefish.com.sg", "Copy plus code": "\uf186\n8PMV+6F Singapore"}}