{"Popular times": {"Monday": {"6 am.": 0, "7 am.": 0, "8 am.": 0, "9 am.": 0, "10 am.": 0, "11 am.": 9, "12 pm.": 3, "1 pm.": 5, "2 pm.": 13, "3 pm.": 16, "4 pm.": 26, "5 pm.": 32, "6 pm.": 54, "7 pm.": 73, "8 pm.": 79, "9 pm.": 75, "10 pm.": 0, "11 pm.": 0}, "Tuesday": {"6 am.": 0, "7 am.": 0, "8 am.": 0, "9 am.": 0, "10 am.": 0, "11 am.": 35, "12 pm.": 26, "1 pm.": 26, "2 pm.": 13, "3 pm.": 5, "4 pm.": 3, "5 pm.": 24, "6 pm.": 64, "7 pm.": 100, "8 pm.": 94, "9 pm.": 50, "10 pm.": 0, "11 pm.": 0}, "Wednesday": {"6 am.": 0, "7 am.": 0, "8 am.": 0, "9 am.": 0, "10 am.": 0, "11 am.": 30, "12 pm.": 33, "1 pm.": 54, "2 pm.": 39, "3 pm.": 24, "4 pm.": 13, "5 pm.": 15, "6 pm.": 22, "7 pm.": 18, "8 pm.": 24, "9 pm.": 11, "10 pm.": 0, "11 pm.": 0}, "Thursday": {"6 am.": 0, "7 am.": 0, "8 am.": 0, "9 am.": 0, "10 am.": 0, "11 am.": 18, "12 pm.": 33, "1 pm.": 71, "2 pm.": 67, "3 pm.": 71, "4 pm.": 71, "5 pm.": 83, "6 pm.": 94, "7 pm.": 66, "8 pm.": 45, "9 pm.": 16, "10 pm.": 0, "11 pm.": 0}, "Friday": {"6 am.": 0, "7 am.": 0, "8 am.": 0, "9 am.": 0, "10 am.": 0, "11 am.": 56, "12 pm.": 52, "1 pm.": 64, "2 pm.": 33, "3 pm.": 18, "4 pm.": 16, "5 pm.": 32, "6 pm.": 43, "7 pm.": 49, "8 pm.": 64, "9 pm.": 58, "10 pm.": 0, "11 pm.": 0}, "Saturday": {"6 am.": 0, "7 am.": 0, "8 am.": 0, "9 am.": 0, "10 am.": 0, "11 am.": 28, "12 pm.": 32, "1 pm.": 37, "2 pm.": 22, "3 pm.": 11, "4 pm.": 7, "5 pm.": 20, "6 pm.": 50, "7 pm.": 66, "8 pm.": 67, "9 pm.": 49, "10 pm.": 0, "11 pm.": 0}, "Sunday": {"6 am.": 0, "7 am.": 0, "8 am.": 0, "9 am.": 0, "10 am.": 0, "11 am.": 13, "12 pm.": 22, "1 pm.": 33, "2 pm.": 37, "3 pm.": 45, "4 pm.": 41, "5 pm.": 24, "6 pm.": 13, "7 pm.": 15, "8 pm.": 33, "9 pm.": 50, "10 pm.": 0, "11 pm.": 0}}, "About": {"Accessibility": ["Wheelchair-accessible car park", "Wheelchair-accessible entrance", "Wheelchair-accessible seating", "Wheelchair-accessible toilet"], "Service options": ["Delivery", "Takeaway", "Dine-in"], "Offerings": ["Alcohol", "Beer", "Coffee", "Small plates", "Wine"], "Dining options": ["Brunch", "Lunch", "Dinner", "Dessert"], "Amenities": ["Toilets"], "Atmosphere": ["Casual", "Cosy"], "Crowd": ["Groups"], "Planning": ["Accepts reservations"], "Payments": ["Credit cards", "NFC mobile payments"], "Children": ["Good for kids", "Kids' menu"], "Parking": ["Paid parking lot", "Paid street parking"]}, "url": "https://www.google.com/maps/place/Saizeriya/data=!4m7!3m6!1s0x31da3d224fa36beb:0xb7fe4a72f99a83a4!8m2!3d1.342467!4d103.9532704!16s%2Fg%2F11bysjvfhc!19sChIJ62ujTyI92jERpIOa-XJK_rc?authuser=0&hl=en&rclk=1", "status": "success", "place_id": "ChIJ62ujTyI92jERpIOa-XJK_rc", "timestamp": "2024-12-12 21:52:00.074629", "metadata": {"Copy address": "\ue0c8\n\u3012528833, Simei Street 6, 3\u53f7 East Point Mall", "Copy website": "\ue14d", "Open website": "\ue80b\nsaizeriya.com.sg", "Copy phone number": "\ue0b0\n6604 8630", "Call phone number": "\ue0b0", "Copy plus code": "\uf186\n8XV3+56 Singapore"}}