{"Popular times": {}, "About": {"Accessibility": ["Wheelchair-accessible car park", "Wheelchair-accessible entrance", "Wheelchair-accessible seating", "Wheelchair-accessible toilet"], "Service options": ["On-site services"], "Amenities": ["Toilets"], "Parking": ["Free of charge street parking", "Free parking lot", "On-site parking"]}, "url": "https://www.google.com/maps/place/Revival+Centre+Church/data=!4m7!3m6!1s0x31da19dd0cdf0109:0xc081614fab8e3a5!8m2!3d1.3191462!4d103.8463532!16s%2Fg%2F1tfrv048!19sChIJCQHfDN0Z2jERpeO4-hQWCAw?authuser=0&hl=en&rclk=1", "status": "success", "place_id": "ChIJCQHfDN0Z2jERpeO4-hQWCAw", "timestamp": "2024-12-09 17:47:19.376463", "metadata": {"Copy address": "\ue0c8\n19 Moulmein Rise, Singapore 308134", "Copy website": "\ue14d", "Open website": "\ue80b\nrevival.org.sg", "Copy phone number": "\ue0b0\n6251 5317", "Call phone number": "\ue0b0", "Copy plus code": "\uf186\n8R9W+MG Singapore"}}