{"Popular times": {}, "About": {"Accessibility": ["Wheelchair-accessible entrance"], "Service options": ["Online classes", "On-site services"], "Children": ["Good for kids"]}, "url": "https://www.google.com/maps/place/POP+Studio+Academy+-+Electronic+Music+Production+%26+DJ+School/data=!4m7!3m6!1s0x31da19a12dcd0205:0x790618f8c150b256!8m2!3d1.3363403!4d103.8840416!16s%2Fg%2F11g9qnnjb9!19sChIJBQLNLaEZ2jERVrJQwfgYBnk?authuser=0&hl=en&rclk", "status": "success", "place_id": "ChIJBQLNLaEZ2jERVrJQwfgYBnk", "timestamp": "2024-12-08 13:05:17.465099", "metadata": {"Copy address": "\ue0c8\n20 Shaw Rd, Singapore 367956", "Open booking link": "\ue878\nwhatsapp.com", "Copy website": "\ue14d", "Open website": "\ue80b\npopstudioacademy.com", "Copy phone number": "\ue0b0\n9766 9493", "Call phone number": "\ue0b0", "Copy plus code": "\uf186\n8VPM+GJ Singapore"}}