{"Popular times": {}, "About": {"Accessibility": ["Wheelchair-accessible car park", "Wheelchair-accessible entrance"], "Service options": ["Online classes", "On-site services"], "Amenities": ["Toilets"]}, "url": "https://www.google.com/maps/place/FUN+TENNIS/data=!4m7!3m6!1s0x31da1951164318c3:0xb363732c26e9f792!8m2!3d1.2877624!4d103.8038714!16s%2Fg%2F11hzpndk8s!19sChIJwxhDFlEZ2jERkvfpJixzY7M?authuser=0&hl=en&rclk=1", "status": "success", "place_id": "ChIJwxhDFlEZ2jERkvfpJixzY7M", "timestamp": "2024-12-09 10:57:53.569380", "metadata": {"Copy address": "\ue0c8\n1 Queensway, Queensway Shopping Centre, #02-10, 149053", "Copy website": "\ue14d", "Open website": "\ue80b\nfuntennis.sg", "Copy phone number": "\ue0b0\n8779 5930", "Call phone number": "\ue0b0", "Copy plus code": "\uf186\n7RQ3+4G Singapore"}}