{"Popular times": {}, "About": {"Accessibility": ["Wheelchair-accessible car park"]}, "url": "https://www.google.com/maps/place/Eshkol+Valley+@+Gospel+Light/data=!4m7!3m6!1s0x31da161d4dee1c8f:0x9b8ae5f31b81713f!8m2!3d1.3915118!4d103.9136275!16s%2Fg%2F11g047z8dr!19sChIJjxzuTR0W2jERP3GBG_Plips?authuser=0&hl=en&rclk=1", "status": "success", "place_id": "ChIJjxzuTR0W2jERP3GBG_Plips", "timestamp": "2024-12-09 21:53:14.716177", "metadata": {"Copy address": "\ue0c8\n39 Punggol Field Walk, Singapore 828753", "Copy website": "\ue14d", "Open website": "\ue80b\neshkolvalley.com.sg", "Copy phone number": "\ue0b0\n8323 2245", "Call phone number": "\ue0b0", "Copy plus code": "\uf186\n9WR7+JF Singapore"}}